[{"line":1,"elements":[{"start_timestamp":"2024-08-23T19:29:28.464Z","line":11,"name":"Add new contacts","description":"","id":"create-new-contacts;add-new-contacts;;2","type":"scenario","keyword":"Scenario Outline","steps":[{"result":{"duration":8055586300,"status":"passed"},"line":4,"name":"User is logged into the application","match":{"location":"com.qa.stepDefinitions.ContactsPageSteps.user_is_logged_into_the_application()"},"keyword":"Given "},{"result":{"duration":4256340900,"status":"passed"},"line":5,"name":"User is on the contacts page","match":{"location":"com.qa.stepDefinitions.ContactsPageSteps.user_is_on_the_contacts_page()"},"keyword":"When "},{"result":{"duration":994800,"status":"passed"},"line":6,"name":"User clicks on New Contacts from the menu","match":{"location":"com.qa.stepDefinitions.ContactsPageSteps.user_clicks_on_new_contacts_from_the_menu()"},"keyword":"Then "},{"result":{"duration":1622339200,"status":"passed"},"line":7,"name":"User enters new contact details Mr., Basil, Arthur, Dell","match":{"arguments":[{"val":"Mr.","offset":32},{"val":" Basil","offset":36},{"val":" Arthur","offset":43},{"val":" Dell","offset":51}],"location":"com.qa.stepDefinitions.ContactsPageSteps.user_enters_new_contact_details(java.lang.String,java.lang.String,java.lang.String,java.lang.String)"},"keyword":"Then "}]},{"start_timestamp":"2024-08-23T19:29:42.450Z","line":12,"name":"Add new contacts","description":"","id":"create-new-contacts;add-new-contacts;;3","type":"scenario","keyword":"Scenario Outline","steps":[{"result":{"duration":7475267100,"status":"passed"},"line":4,"name":"User is logged into the application","match":{"location":"com.qa.stepDefinitions.ContactsPageSteps.user_is_logged_into_the_application()"},"keyword":"Given "},{"result":{"duration":4182751500,"status":"passed"},"line":5,"name":"User is on the contacts page","match":{"location":"com.qa.stepDefinitions.ContactsPageSteps.user_is_on_the_contacts_page()"},"keyword":"When "},{"result":{"duration":998100,"status":"passed"},"line":6,"name":"User clicks on New Contacts from the menu","match":{"location":"com.qa.stepDefinitions.ContactsPageSteps.user_clicks_on_new_contacts_from_the_menu()"},"keyword":"Then "},{"result":{"duration":1668052700,"status":"passed"},"line":7,"name":"User enters new contact details Miss, Dean, Amy, Bell","match":{"arguments":[{"val":"Miss","offset":32},{"val":" Dean","offset":37},{"val":" Amy","offset":43},{"val":" Bell","offset":48}],"location":"com.qa.stepDefinitions.ContactsPageSteps.user_enters_new_contact_details(java.lang.String,java.lang.String,java.lang.String,java.lang.String)"},"keyword":"Then "}]}],"name":"Create new contacts","description":"","id":"create-new-contacts","keyword":"Feature","uri":"file:src/test/resource/com/qa/features/homePage.feature","tags":[]}]